{
  "peak_cpu_memory_MB": 1673.372,
  "peak_gpu_0_memory_MB": 11,
  "peak_gpu_1_memory_MB": 3970,
  "peak_gpu_2_memory_MB": 11,
  "peak_gpu_3_memory_MB": 11,
  "peak_gpu_4_memory_MB": 11,
  "peak_gpu_5_memory_MB": 11,
  "peak_gpu_6_memory_MB": 11,
  "peak_gpu_7_memory_MB": 11,
  "peak_gpu_8_memory_MB": 11,
  "peak_gpu_9_memory_MB": 11,
  "peak_gpu_10_memory_MB": 11,
  "peak_gpu_11_memory_MB": 9142,
  "peak_gpu_12_memory_MB": 11,
  "peak_gpu_13_memory_MB": 11,
  "peak_gpu_14_memory_MB": 11,
  "peak_gpu_15_memory_MB": 11,
  "training_duration": "00:04:11",
  "training_start_epoch": 0,
  "training_epochs": 7,
  "epoch": 7,
  "training_1_F1": 0.7957639939485128,
  "training_0_F1": 0.7919876733435556,
  "training_accuracy": 0.7938931297709924,
  "training_average_F1": 0.7938758336460342,
  "training_loss": 0.4373591660362918,
  "training_cpu_memory_MB": 1673.372,
  "training_gpu_0_memory_MB": 11,
  "training_gpu_1_memory_MB": 3970,
  "training_gpu_2_memory_MB": 11,
  "training_gpu_3_memory_MB": 11,
  "training_gpu_4_memory_MB": 11,
  "training_gpu_5_memory_MB": 11,
  "training_gpu_6_memory_MB": 11,
  "training_gpu_7_memory_MB": 11,
  "training_gpu_8_memory_MB": 11,
  "training_gpu_9_memory_MB": 11,
  "training_gpu_10_memory_MB": 11,
  "training_gpu_11_memory_MB": 9142,
  "training_gpu_12_memory_MB": 11,
  "training_gpu_13_memory_MB": 11,
  "training_gpu_14_memory_MB": 11,
  "training_gpu_15_memory_MB": 11,
  "validation_1_F1": 0.6259541984732353,
  "validation_0_F1": 0.7461139896372571,
  "validation_accuracy": 0.6975308641975309,
  "validation_average_F1": 0.6860340940552462,
  "validation_loss": 0.6155661371621218,
  "best_epoch": 6,
  "best_validation_1_F1": 0.7599999999999504,
  "best_validation_0_F1": 0.7931034482758124,
  "best_validation_accuracy": 0.7777777777777778,
  "best_validation_average_F1": 0.7765517241378814,
  "best_validation_loss": 0.5327282385392622
}